CHANGELOG.md
LICENSE
MANIFEST.in
README.rst
setup.cfg
setup.py
django_toolkit/__init__.py
django_toolkit/cls.py
django_toolkit/date_util.py
django_toolkit/datetime_util.py
django_toolkit/decorators.py
django_toolkit/dict_helper.py
django_toolkit/email.py
django_toolkit/fields.py
django_toolkit/file.py
django_toolkit/font_awesome.py
django_toolkit/json.py
django_toolkit/log.py
django_toolkit/monkeypatches.py
django_toolkit/network.py
django_toolkit/numeric.py
django_toolkit/pagination.py
django_toolkit/storage.py
django_toolkit/view_decorators.py
django_toolkit/views.py
django_toolkit/xml_utils.py
django_toolkit.egg-info/PKG-INFO
django_toolkit.egg-info/SOURCES.txt
django_toolkit.egg-info/dependency_links.txt
django_toolkit.egg-info/not-zip-safe
django_toolkit.egg-info/requires.txt
django_toolkit.egg-info/top_level.txt
django_toolkit/celery/__init__.py
django_toolkit/celery/decorators.py
django_toolkit/csv/__init__.py
django_toolkit/csv/unicode.py
django_toolkit/db/__init__.py
django_toolkit/db/fields.py
django_toolkit/db/model_utils.py
django_toolkit/db/models.py
django_toolkit/db/mptt.py
django_toolkit/forms/__init__.py
django_toolkit/forms/comment.py
django_toolkit/forms/crispy.py
django_toolkit/forms/fields.py
django_toolkit/forms/formsets.py
django_toolkit/forms/widgets.py
django_toolkit/markup/__init__.py
django_toolkit/markup/comment_helper.py
django_toolkit/markup/html.py
django_toolkit/models/__init__.py
django_toolkit/models/decorators.py
django_toolkit/table/__init__.py
django_toolkit/table/console.py
django_toolkit/templatetags/__init__.py
django_toolkit/templatetags/a_tag.py
django_toolkit/templatetags/actions.py
django_toolkit/templatetags/attr.py
django_toolkit/templatetags/buttons.py
django_toolkit/templatetags/cache_helpers.py
django_toolkit/templatetags/captureas.py
django_toolkit/templatetags/comment_utils.py
django_toolkit/templatetags/foreign_a.py
django_toolkit/templatetags/html2text.py
django_toolkit/templatetags/sliced_pagination.py
django_toolkit/templatetags/url_helpers.py
django_toolkit/tests/__init__.py
django_toolkit/tests/date_util.py
django_toolkit/tests/datetime_util.py
django_toolkit/tests/markup.py
django_toolkit/tests/pagination.py
